pycolorcli/__init__.py
pycolorcli/color.py
pycolorcli/effect.py
pycolorcli/rgb.py
pycolorcli/util.py
pycolorcli-2.0.0.dist-info/METADATA
pycolorcli-2.0.0.dist-info/WHEEL
pycolorcli-2.0.0.dist-info/top_level.txt
pycolorcli-2.0.0.dist-info/RECORD
