Metadata-Version: 2.4
Name: pycolorcli
Version: 2.0.0
Summary: Library lengkap untuk warna teks terminal, efek animasi, dan RGB, dibuat dari dasar.
Author: ATHALLAH RAJENDRA PUTRA JUNIARTO
Requires-Python: >=3.13
Dynamic: author
Dynamic: requires-python
Dynamic: summary
